Metadata-Version: 2.1
Name: azureai-statsig
Version: 0.1.0
Summary: Statsig wrapped Azure AI inference library
Home-page: https://github.com/statsig-io/azureai-python
Author: Kenny Yi
Author-email: kenny@statsig.com
License: ISC
Classifier: Intended Audience :: Developers
Classifier: Programming Language :: Python
Classifier: Programming Language :: Python :: 3
Classifier: Topic :: Software Development :: Libraries
Requires-Python: >=3.8
License-File: LICENSE
Requires-Dist: statsig
Requires-Dist: azure-ai-inference
